{
    "dni": 1000.0,
    "generated_rays": 27659902,
    "power_per_ray": 0.03741914385999226,
    "num_rays": 812102.0,
    "avg_flux": 1700.6943527552921,
    "peak_flux": 4865.741364889242,
    "min_flux": 0.0,
    "radius": 0.0,
    "bin_size_x": 0.11912060709304066,
    "bin_size_y": 6.0,
    "xvalues": [
        -0.23824121418608132,
        -0.11912060709304068,
        0.0,
        0.11912060709304068,
        0.23824121418608135
    ],
    "yvalues": [
        -12.0,
        -6.0,
        0.0,
        6.0,
        12.0
    ],
    "flux": [
        [
            0.0,
            0.0,
            0.0,
            0.0,
            0.0
        ],
        [
            4482.0,
            4605.0,
            4634.0,
            4600.0,
            4661.0
        ],
        [
            73793.0,
            92938.0,
            92920.0,
            92524.0,
            92512.0
        ],
        [
            56520.0,
            72129.0,
            72340.0,
            71566.0,
            71878.0
        ],
        [
            0.0,
            0.0,
            0.0,
            0.0,
            0.0
        ]
    ],
    "sim_time": 26.814283847808838
}