{
    "dni": 1000.0,
    "generated_rays": 16735827,
    "power_per_ray": 0.06256162394305971,
    "num_rays": 790337.0,
    "avg_flux": 2767.210330712218,
    "peak_flux": 9371.065873968593,
    "min_flux": 0.0,
    "radius": 0.0,
    "bin_size_x": 0.11912060709304066,
    "bin_size_y": 6.0,
    "xvalues": [
        -0.23824121418608132,
        -0.11912060709304068,
        0.0,
        0.11912060709304068,
        0.23824121418608135
    ],
    "yvalues": [
        -12.0,
        -6.0,
        0.0,
        6.0,
        12.0
    ],
    "flux": [
        [
            0.0,
            0.0,
            0.0,
            0.0,
            0.0
        ],
        [
            36287.0,
            50762.0,
            50790.0,
            51205.0,
            50837.0
        ],
        [
            75275.0,
            107058.0,
            106796.0,
            106381.0,
            106127.0
        ],
        [
            7599.0,
            10305.0,
            10309.0,
            10352.0,
            10254.0
        ],
        [
            0.0,
            0.0,
            0.0,
            0.0,
            0.0
        ]
    ],
    "sim_time": 18.482045650482178
}