{
    "dni": 1000.0,
    "generated_rays": 4208103,
    "power_per_ray": 0.3410773737546888,
    "num_rays": 916113.0,
    "avg_flux": 30602.09426842985,
    "peak_flux": 81515.62699240449,
    "min_flux": 3401.3907114983303,
    "radius": 0.0,
    "bin_size_x": 0.06807059529144252,
    "bin_size_y": 6.0,
    "xvalues": [
        -0.13614119058288504,
        -0.0680705952914425,
        2.7755575615628914e-17,
        0.06807059529144252,
        0.13614119058288507
    ],
    "yvalues": [
        -12.0,
        -6.0,
        0.0,
        6.0,
        12.0
    ],
    "flux": [
        [
            4073.0,
            5665.0,
            5864.0,
            5711.0,
            5856.0
        ],
        [
            31476.0,
            41147.0,
            41576.0,
            41690.0,
            41803.0
        ],
        [
            74474.0,
            97342.0,
            97611.0,
            97436.0,
            97571.0
        ],
        [
            31466.0,
            42091.0,
            42078.0,
            41487.0,
            42151.0
        ],
        [
            4195.0,
            5847.0,
            5792.0,
            5841.0,
            5870.0
        ]
    ],
    "sim_time": 14.23016095161438
}