{
    "dni": 1000.0,
    "generated_rays": 8264730,
    "power_per_ray": 0.14163970193279712,
    "num_rays": 927262.0,
    "avg_flux": 12862.833820417643,
    "peak_flux": 24615.24039967733,
    "min_flux": 2353.7051323998653,
    "radius": 0.0,
    "bin_size_x": 0.06807059529144252,
    "bin_size_y": 6.0,
    "xvalues": [
        -0.13614119058288504,
        -0.0680705952914425,
        2.7755575615628914e-17,
        0.06807059529144252,
        0.13614119058288507
    ],
    "yvalues": [
        -12.0,
        -6.0,
        0.0,
        6.0,
        12.0
    ],
    "flux": [
        [
            6848.0,
            6906.0,
            6878.0,
            6815.0,
            6787.0
        ],
        [
            25970.0,
            26322.0,
            25981.0,
            25733.0,
            25789.0
        ],
        [
            70298.0,
            70474.0,
            70979.0,
            70368.0,
            70115.0
        ],
        [
            62325.0,
            62068.0,
            61966.0,
            62337.0,
            61994.0
        ],
        [
            20002.0,
            20307.0,
            19994.0,
            20042.0,
            19964.0
        ]
    ],
    "sim_time": 17.70853042602539
}