{
    "dni": 1000.0,
    "generated_rays": 4253951,
    "power_per_ray": 0.34326886044151156,
    "num_rays": 884016.0,
    "avg_flux": 29719.652431697585,
    "peak_flux": 73128.68880284902,
    "min_flux": 3998.969087381255,
    "radius": 0.0,
    "bin_size_x": 0.06807059529144252,
    "bin_size_y": 6.0,
    "xvalues": [
        -0.13614119058288504,
        -0.0680705952914425,
        2.7755575615628914e-17,
        0.06807059529144252,
        0.13614119058288507
    ],
    "yvalues": [
        -12.0,
        -6.0,
        0.0,
        6.0,
        12.0
    ],
    "flux": [
        [
            4758.0,
            8414.0,
            8484.0,
            8354.0,
            8530.0
        ],
        [
            26910.0,
            43731.0,
            44372.0,
            43631.0,
            43855.0
        ],
        [
            54915.0,
            86944.0,
            86950.0,
            86300.0,
            87009.0
        ],
        [
            27103.0,
            43702.0,
            43530.0,
            43802.0,
            43967.0
        ],
        [
            4974.0,
            8478.0,
            8513.0,
            8344.0,
            8446.0
        ]
    ],
    "sim_time": 8.828155279159546
}