{
    "dni": 1000.0,
    "generated_rays": 4771636,
    "power_per_ray": 0.3145078067647324,
    "num_rays": 837443.0,
    "avg_flux": 25795.020604987407,
    "peak_flux": 63899.7700387507,
    "min_flux": 2417.9664974111806,
    "radius": 0.0,
    "bin_size_x": 0.06807059529144252,
    "bin_size_y": 6.0,
    "xvalues": [
        -0.13614119058288504,
        -0.0680705952914425,
        2.7755575615628914e-17,
        0.06807059529144252,
        0.13614119058288507
    ],
    "yvalues": [
        -12.0,
        -6.0,
        0.0,
        6.0,
        12.0
    ],
    "flux": [
        [
            3140.0,
            9372.0,
            9425.0,
            9363.0,
            9262.0
        ],
        [
            17716.0,
            43291.0,
            43523.0,
            43523.0,
            43102.0
        ],
        [
            35206.0,
            82981.0,
            82516.0,
            82571.0,
            82905.0
        ],
        [
            18322.0,
            44598.0,
            44629.0,
            44334.0,
            44172.0
        ],
        [
            3458.0,
            10137.0,
            9913.0,
            9931.0,
            10053.0
        ]
    ],
    "sim_time": 8.936109781265259
}