{
    "dni": 1000.0,
    "generated_rays": 12301860,
    "power_per_ray": 0.09972380980919497,
    "num_rays": 861381.0,
    "avg_flux": 8412.853807577723,
    "peak_flux": 16253.505690543045,
    "min_flux": 1416.172172475095,
    "radius": 0.0,
    "bin_size_x": 0.06807059529144252,
    "bin_size_y": 6.0,
    "xvalues": [
        -0.13614119058288504,
        -0.0680705952914425,
        2.7755575615628914e-17,
        0.06807059529144252,
        0.13614119058288507
    ],
    "yvalues": [
        -12.0,
        -6.0,
        0.0,
        6.0,
        12.0
    ],
    "flux": [
        [
            25507.0,
            30304.0,
            30168.0,
            30019.0,
            29826.0
        ],
        [
            56619.0,
            66567.0,
            66486.0,
            66069.0,
            66233.0
        ],
        [
            47653.0,
            54182.0,
            54727.0,
            54270.0,
            54189.0
        ],
        [
            17663.0,
            20006.0,
            19638.0,
            19782.0,
            19837.0
        ],
        [
            5800.0,
            6393.0,
            6660.0,
            6438.0,
            6345.0
        ]
    ],
    "sim_time": 11.3233802318573
}