{
    "dni": 1000.0,
    "generated_rays": 3886763,
    "power_per_ray": 0.32520915316568466,
    "num_rays": 951113.0,
    "avg_flux": 30293.12455895414,
    "peak_flux": 66182.2946896581,
    "min_flux": 7417.111722441441,
    "radius": 0.0,
    "bin_size_x": 0.06807059529144252,
    "bin_size_y": 6.0,
    "xvalues": [
        -0.13614119058288504,
        -0.0680705952914425,
        2.7755575615628914e-17,
        0.06807059529144252,
        0.13614119058288507
    ],
    "yvalues": [
        -12.0,
        -6.0,
        0.0,
        6.0,
        12.0
    ],
    "flux": [
        [
            9488.0,
            9489.0,
            9607.0,
            9315.0,
            9473.0
        ],
        [
            43534.0,
            43477.0,
            43331.0,
            44028.0,
            43339.0
        ],
        [
            82612.0,
            83117.0,
            82666.0,
            82777.0,
            82939.0
        ],
        [
            44241.0,
            44259.0,
            44040.0,
            44268.0,
            44253.0
        ],
        [
            10304.0,
            10055.0,
            10189.0,
            10252.0,
            10060.0
        ]
    ],
    "sim_time": 8.866549491882324
}