{
    "dni": 1000.0,
    "generated_rays": 15609138,
    "power_per_ray": 0.10882516916498705,
    "num_rays": 439631.0,
    "avg_flux": 4685.617702262794,
    "peak_flux": 55372.40078486506,
    "min_flux": 0.0,
    "radius": 0.0,
    "bin_size_x": 0.06807059529144252,
    "bin_size_y": 6.0,
    "xvalues": [
        -0.13614119058288504,
        -0.0680705952914425,
        2.7755575615628914e-17,
        0.06807059529144252,
        0.13614119058288507
    ],
    "yvalues": [
        -12.0,
        -6.0,
        0.0,
        6.0,
        12.0
    ],
    "flux": [
        [
            0.0,
            0.0,
            0.0,
            0.0,
            0.0
        ],
        [
            0.0,
            0.0,
            56.0,
            7053.0,
            16490.0
        ],
        [
            0.0,
            0.0,
            20308.0,
            156702.0,
            207814.0
        ],
        [
            0.0,
            0.0,
            202.0,
            9342.0,
            21603.0
        ],
        [
            0.0,
            0.0,
            0.0,
            0.0,
            61.0
        ]
    ],
    "sim_time": 15.760224342346191
}