{
    "dni": 1000.0,
    "generated_rays": 4954057,
    "power_per_ray": 0.25524125423461363,
    "num_rays": 1199018.0,
    "avg_flux": 29972.692992187538,
    "peak_flux": 117855.40918953424,
    "min_flux": 290.5982696124496,
    "radius": 0.0,
    "bin_size_x": 0.06807059529144252,
    "bin_size_y": 6.0,
    "xvalues": [
        -0.13614119058288504,
        -0.0680705952914425,
        2.7755575615628914e-17,
        0.06807059529144252,
        0.13614119058288507
    ],
    "yvalues": [
        -12.0,
        -6.0,
        0.0,
        6.0,
        12.0
    ],
    "flux": [
        [
            465.0,
            558.0,
            559.0,
            582.0,
            566.0
        ],
        [
            22987.0,
            25145.0,
            25225.0,
            24991.0,
            25023.0
        ],
        [
            172046.0,
            188586.0,
            187592.0,
            188121.0,
            187366.0
        ],
        [
            24911.0,
            27312.0,
            27661.0,
            27747.0,
            27827.0
        ],
        [
            2493.0,
            2809.0,
            2804.0,
            2837.0,
            2805.0
        ]
    ],
    "sim_time": 11.638827085494995
}