{
    "dni": 1000.0,
    "generated_rays": 3870354,
    "power_per_ray": 0.31936304442154545,
    "num_rays": 976256.0,
    "avg_flux": 30534.974948671228,
    "peak_flux": 117962.80344964827,
    "min_flux": 333.1067703587467,
    "radius": 0.0,
    "bin_size_x": 0.06807059529144252,
    "bin_size_y": 6.0,
    "xvalues": [
        -0.13614119058288504,
        -0.0680705952914425,
        2.7755575615628914e-17,
        0.06807059529144252,
        0.13614119058288507
    ],
    "yvalues": [
        -12.0,
        -6.0,
        0.0,
        6.0,
        12.0
    ],
    "flux": [
        [
            2247.0,
            2216.0,
            2297.0,
            2239.0,
            2236.0
        ],
        [
            22220.0,
            21841.0,
            22233.0,
            22260.0,
            22267.0
        ],
        [
            150117.0,
            150125.0,
            150859.0,
            150248.0,
            149966.0
        ],
        [
            20126.0,
            20057.0,
            20063.0,
            20130.0,
            20306.0
        ],
        [
            426.0,
            442.0,
            437.0,
            439.0,
            459.0
        ]
    ],
    "sim_time": 16.019075632095337
}