{
    "dni": 1000.0,
    "generated_rays": 6662727,
    "power_per_ray": 0.2114366657214603,
    "num_rays": 1083356.0,
    "avg_flux": 22433.68857959091,
    "peak_flux": 89714.06743898973,
    "min_flux": 723.2124746087276,
    "radius": 0.0,
    "bin_size_x": 0.06807059529144252,
    "bin_size_y": 6.0,
    "xvalues": [
        -0.13614119058288504,
        -0.0680705952914425,
        2.7755575615628914e-17,
        0.06807059529144252,
        0.13614119058288507
    ],
    "yvalues": [
        -12.0,
        -6.0,
        0.0,
        6.0,
        12.0
    ],
    "flux": [
        [
            1397.0,
            4154.0,
            4143.0,
            4144.0,
            4168.0
        ],
        [
            12966.0,
            29809.0,
            29414.0,
            29362.0,
            29473.0
        ],
        [
            76671.0,
            173297.0,
            171912.0,
            172712.0,
            172231.0
        ],
        [
            12609.0,
            30779.0,
            31125.0,
            31184.0,
            31213.0
        ],
        [
            2237.0,
            7003.0,
            7171.0,
            7048.0,
            7134.0
        ]
    ],
    "sim_time": 11.408111095428467
}