{
    "dni": 1000.0,
    "generated_rays": 47620909,
    "power_per_ray": 0.021654357039663293,
    "num_rays": 831543.0,
    "avg_flux": 1007.7477751473908,
    "peak_flux": 2991.8805400263377,
    "min_flux": 0.0,
    "radius": 0.0,
    "bin_size_x": 0.11912060709304066,
    "bin_size_y": 6.0,
    "xvalues": [
        -0.23824121418608132,
        -0.11912060709304068,
        0.0,
        0.11912060709304068,
        0.23824121418608135
    ],
    "yvalues": [
        -12.0,
        -6.0,
        0.0,
        6.0,
        12.0
    ],
    "flux": [
        [
            3.0,
            3.0,
            1.0,
            1.0,
            1.0
        ],
        [
            79847.0,
            98665.0,
            98681.0,
            98504.0,
            98750.0
        ],
        [
            57445.0,
            67480.0,
            66886.0,
            67234.0,
            67209.0
        ],
        [
            6341.0,
            6028.0,
            6239.0,
            6059.0,
            6166.0
        ],
        [
            0.0,
            0.0,
            0.0,
            0.0,
            0.0
        ]
    ],
    "sim_time": 42.009342670440674
}