{
    "dni": 1000.0,
    "generated_rays": 6554182,
    "power_per_ray": 0.25050960280824397,
    "num_rays": 683340.0,
    "avg_flux": 16765.26467363955,
    "peak_flux": 46539.716233564126,
    "min_flux": 0.0,
    "radius": 0.0,
    "bin_size_x": 0.06807059529144252,
    "bin_size_y": 6.0,
    "xvalues": [
        -0.13614119058288504,
        -0.0680705952914425,
        2.7755575615628914e-17,
        0.06807059529144252,
        0.13614119058288507
    ],
    "yvalues": [
        -12.0,
        -6.0,
        0.0,
        6.0,
        12.0
    ],
    "flux": [
        [
            0.0,
            5873.0,
            11543.0,
            11562.0,
            11818.0
        ],
        [
            0.0,
            28351.0,
            44262.0,
            44043.0,
            44505.0
        ],
        [
            0.0,
            50764.0,
            75877.0,
            75665.0,
            74956.0
        ],
        [
            0.0,
            28697.0,
            44823.0,
            44500.0,
            44542.0
        ],
        [
            0.0,
            6121.0,
            11817.0,
            11929.0,
            11692.0
        ]
    ],
    "sim_time": 8.995945453643799
}