{
    "dni": 1000.0,
    "generated_rays": 11440642,
    "power_per_ray": 0.14849970025196416,
    "num_rays": 347544.0,
    "avg_flux": 5054.57406421485,
    "peak_flux": 19269.305590169475,
    "min_flux": 0.0,
    "radius": 0.0,
    "bin_size_x": 0.06807059529144252,
    "bin_size_y": 6.0,
    "xvalues": [
        -0.13614119058288504,
        -0.0680705952914425,
        2.7755575615628914e-17,
        0.06807059529144252,
        0.13614119058288507
    ],
    "yvalues": [
        -12.0,
        -6.0,
        0.0,
        6.0,
        12.0
    ],
    "flux": [
        [
            0.0,
            0.0,
            2336.0,
            14869.0,
            19769.0
        ],
        [
            0.0,
            0.0,
            7098.0,
            34343.0,
            40835.0
        ],
        [
            0.0,
            0.0,
            10116.0,
            45714.0,
            52997.0
        ],
        [
            0.0,
            0.0,
            7268.0,
            34086.0,
            40708.0
        ],
        [
            0.0,
            0.0,
            2346.0,
            15148.0,
            19911.0
        ]
    ],
    "sim_time": 9.817462682723999
}