{
    "dni": 1000.0,
    "generated_rays": 12196567,
    "power_per_ray": 0.08090569786800647,
    "num_rays": 786456.0,
    "avg_flux": 3561.0279405187403,
    "peak_flux": 8469.290985564709,
    "min_flux": 0.9055886001298841,
    "radius": 0.0,
    "bin_size_x": 0.11912060709304066,
    "bin_size_y": 6.0,
    "xvalues": [
        -0.23824121418608132,
        -0.11912060709304068,
        0.0,
        0.11912060709304068,
        0.23824121418608135
    ],
    "yvalues": [
        -12.0,
        -6.0,
        0.0,
        6.0,
        12.0
    ],
    "flux": [
        [
            8.0,
            11.0,
            8.0,
            9.0,
            12.0
        ],
        [
            40487.0,
            42118.0,
            42232.0,
            42068.0,
            42186.0
        ],
        [
            71580.0,
            74818.0,
            74791.0,
            74312.0,
            74367.0
        ],
        [
            40335.0,
            41911.0,
            41559.0,
            41492.0,
            42089.0
        ],
        [
            17.0,
            12.0,
            10.0,
            12.0,
            12.0
        ]
    ],
    "sim_time": 15.58454179763794
}