{
    "dni": 1000.0,
    "generated_rays": 43760174,
    "power_per_ray": 0.022975209991699615,
    "num_rays": 859587.0,
    "avg_flux": 1105.2770976175289,
    "peak_flux": 3174.730173845252,
    "min_flux": 0.0,
    "radius": 0.0,
    "bin_size_x": 0.11912060709304066,
    "bin_size_y": 6.0,
    "xvalues": [
        -0.23824121418608132,
        -0.11912060709304068,
        0.0,
        0.11912060709304068,
        0.23824121418608135
    ],
    "yvalues": [
        -12.0,
        -6.0,
        0.0,
        6.0,
        12.0
    ],
    "flux": [
        [
            3.0,
            4.0,
            3.0,
            2.0,
            2.0
        ],
        [
            95700.0,
            98657.0,
            98761.0,
            98497.0,
            98738.0
        ],
        [
            66293.0,
            68275.0,
            67603.0,
            68184.0,
            67906.0
        ],
        [
            6215.0,
            6129.0,
            6307.0,
            6160.0,
            6148.0
        ],
        [
            0.0,
            0.0,
            0.0,
            0.0,
            0.0
        ]
    ],
    "sim_time": 38.799423933029175
}