{
    "dni": 1000.0,
    "generated_rays": 13133910,
    "power_per_ray": 0.07717586512271478,
    "num_rays": 766053.0,
    "avg_flux": 3308.7363833795757,
    "peak_flux": 8026.262024722417,
    "min_flux": 1.403740112757684,
    "radius": 0.0,
    "bin_size_x": 0.11912060709304066,
    "bin_size_y": 6.0,
    "xvalues": [
        -0.23824121418608132,
        -0.11912060709304068,
        0.0,
        0.11912060709304068,
        0.23824121418608135
    ],
    "yvalues": [
        -12.0,
        -6.0,
        0.0,
        6.0,
        12.0
    ],
    "flux": [
        [
            20.0,
            20.0,
            15.0,
            14.0,
            13.0
        ],
        [
            35840.0,
            41819.0,
            41960.0,
            41871.0,
            41931.0
        ],
        [
            63992.0,
            74330.0,
            73966.0,
            74331.0,
            73974.0
        ],
        [
            35874.0,
            41517.0,
            41547.0,
            41153.0,
            41731.0
        ],
        [
            32.0,
            29.0,
            27.0,
            27.0,
            20.0
        ]
    ],
    "sim_time": 16.232659339904785
}