{
    "dni": 1000.0,
    "generated_rays": 18600895,
    "power_per_ray": 0.05499711314822253,
    "num_rays": 820221.0,
    "avg_flux": 2524.6002486826737,
    "peak_flux": 8102.321910346181,
    "min_flux": 0.0,
    "radius": 0.0,
    "bin_size_x": 0.11912060709304066,
    "bin_size_y": 6.0,
    "xvalues": [
        -0.23824121418608132,
        -0.11912060709304068,
        0.0,
        0.11912060709304068,
        0.23824121418608135
    ],
    "yvalues": [
        -12.0,
        -6.0,
        0.0,
        6.0,
        12.0
    ],
    "flux": [
        [
            4.0,
            8.0,
            11.0,
            13.0,
            7.0
        ],
        [
            50774.0,
            58188.0,
            58212.0,
            58053.0,
            58243.0
        ],
        [
            91536.0,
            105224.0,
            104838.0,
            104739.0,
            105295.0
        ],
        [
            4786.0,
            5050.0,
            5087.0,
            5191.0,
            4962.0
        ],
        [
            0.0,
            0.0,
            0.0,
            0.0,
            0.0
        ]
    ],
    "sim_time": 20.47409224510193
}