{
    "dni": 1000.0,
    "generated_rays": 46683342,
    "power_per_ray": 0.023233794090444307,
    "num_rays": 505060.0,
    "avg_flux": 656.7271233014259,
    "peak_flux": 2550.464134953435,
    "min_flux": 0.0,
    "radius": 0.0,
    "bin_size_x": 0.11912060709304066,
    "bin_size_y": 6.0,
    "xvalues": [
        -0.23824121418608132,
        -0.11912060709304068,
        0.0,
        0.11912060709304068,
        0.23824121418608135
    ],
    "yvalues": [
        -12.0,
        -6.0,
        0.0,
        6.0,
        12.0
    ],
    "flux": [
        [
            0.0,
            81.0,
            3774.0,
            3838.0,
            3339.0
        ],
        [
            0.0,
            1305.0,
            45289.0,
            46158.0,
            37871.0
        ],
        [
            0.0,
            2235.0,
            77738.0,
            78458.0,
            63376.0
        ],
        [
            0.0,
            1235.0,
            45057.0,
            46215.0,
            38018.0
        ],
        [
            0.0,
            76.0,
            3745.0,
            3872.0,
            3380.0
        ]
    ],
    "sim_time": 40.06979060173035
}