{
    "dni": 1000.0,
    "generated_rays": 17252877,
    "power_per_ray": 0.09026736167641951,
    "num_rays": 305735.0,
    "avg_flux": 2702.869641336365,
    "peak_flux": 5824.605175051807,
    "min_flux": 0.0,
    "radius": 0.0,
    "bin_size_x": 0.06807059529144252,
    "bin_size_y": 6.0,
    "xvalues": [
        -0.13614119058288504,
        -0.0680705952914425,
        2.7755575615628914e-17,
        0.06807059529144252,
        0.13614119058288507
    ],
    "yvalues": [
        -12.0,
        -6.0,
        0.0,
        6.0,
        12.0
    ],
    "flux": [
        [
            0.0,
            15024.0,
            18208.0,
            18389.0,
            18176.0
        ],
        [
            0.0,
            26354.0,
            25301.0,
            25508.0,
            25721.0
        ],
        [
            0.0,
            25863.0,
            17302.0,
            17471.0,
            17387.0
        ],
        [
            0.0,
            16146.0,
            7504.0,
            7424.0,
            7423.0
        ],
        [
            0.0,
            6651.0,
            3206.0,
            3313.0,
            3364.0
        ]
    ],
    "sim_time": 28.600560903549194
}