{
    "dni": 1000.0,
    "generated_rays": 172429880,
    "power_per_ray": 0.009031913077465342,
    "num_rays": 3061810.0,
    "avg_flux": 2708.3649125650854,
    "peak_flux": 5868.14903985262,
    "min_flux": 0.0,
    "radius": 0.0,
    "bin_size_x": 0.06807059529144252,
    "bin_size_y": 6.0,
    "xvalues": [
        -0.13614119058288504,
        -0.0680705952914425,
        2.7755575615628914e-17,
        0.06807059529144252,
        0.13614119058288507
    ],
    "yvalues": [
        -12.0,
        -6.0,
        0.0,
        6.0,
        12.0
    ],
    "flux": [
        [
            0.0,
            148909.0,
            182748.0,
            183577.0,
            182403.0
        ],
        [
            0.0,
            265358.0,
            255935.0,
            255741.0,
            254141.0
        ],
        [
            0.0,
            258031.0,
            173723.0,
            173187.0,
            173700.0
        ],
        [
            0.0,
            160208.0,
            75241.0,
            75776.0,
            75505.0
        ],
        [
            0.0,
            67248.0,
            33313.0,
            33617.0,
            33449.0
        ]
    ],
    "sim_time": 71.05829119682312
}