{
    "dni": 1000.0,
    "generated_rays": 387860,
    "power_per_ray": 3.5451211663952322,
    "num_rays": 95973.0,
    "avg_flux": 33321.86849507615,
    "peak_flux": 80663.34383752271,
    "min_flux": 5859.007542271368,
    "radius": 0.0,
    "bin_size_x": 0.06807059529144252,
    "bin_size_y": 6.0,
    "xvalues": [
        -0.13614119058288504,
        -0.0680705952914425,
        2.7755575615628914e-17,
        0.06807059529144252,
        0.13614119058288507
    ],
    "yvalues": [
        -12.0,
        -6.0,
        0.0,
        6.0,
        12.0
    ],
    "flux": [
        [
            707.0,
            724.0,
            730.0,
            697.0,
            741.0
        ],
        [
            4355.0,
            4475.0,
            4289.0,
            4437.0,
            4347.0
        ],
        [
            8991.0,
            9066.0,
            9238.0,
            9293.0,
            9081.0
        ],
        [
            4266.0,
            4240.0,
            4279.0,
            4159.0,
            4335.0
        ],
        [
            701.0,
            724.0,
            701.0,
            675.0,
            722.0
        ]
    ],
    "sim_time": 1.6247186660766602
}