{
    "dni": 1000.0,
    "generated_rays": 1734150,
    "power_per_ray": 0.8980605415435685,
    "num_rays": 30675.0,
    "avg_flux": 2697.9840555140217,
    "peak_flux": 5833.538467219804,
    "min_flux": 0.0,
    "radius": 0.0,
    "bin_size_x": 0.06807059529144252,
    "bin_size_y": 6.0,
    "xvalues": [
        -0.13614119058288504,
        -0.0680705952914425,
        2.7755575615628914e-17,
        0.06807059529144252,
        0.13614119058288507
    ],
    "yvalues": [
        -12.0,
        -6.0,
        0.0,
        6.0,
        12.0
    ],
    "flux": [
        [
            0.0,
            1530.0,
            1836.0,
            1832.0,
            1767.0
        ],
        [
            0.0,
            2653.0,
            2571.0,
            2621.0,
            2600.0
        ],
        [
            0.0,
            2615.0,
            1628.0,
            1721.0,
            1743.0
        ],
        [
            0.0,
            1583.0,
            756.0,
            767.0,
            770.0
        ],
        [
            0.0,
            679.0,
            332.0,
            339.0,
            332.0
        ]
    ],
    "sim_time": 2.96169114112854
}