{
    "dni": 1000.0,
    "generated_rays": 386365,
    "power_per_ray": 3.5588386515291366,
    "num_rays": 96013.0,
    "avg_flux": 33464.74582613433,
    "peak_flux": 80478.78736477785,
    "min_flux": 6108.231912376491,
    "radius": 0.0,
    "bin_size_x": 0.06807059529144252,
    "bin_size_y": 6.0,
    "xvalues": [
        -0.13614119058288504,
        -0.0680705952914425,
        2.7755575615628914e-17,
        0.06807059529144252,
        0.13614119058288507
    ],
    "yvalues": [
        -12.0,
        -6.0,
        0.0,
        6.0,
        12.0
    ],
    "flux": [
        [
            766.0,
            762.0,
            701.0,
            731.0,
            742.0
        ],
        [
            4316.0,
            4363.0,
            4363.0,
            4233.0,
            4106.0
        ],
        [
            9109.0,
            9002.0,
            9102.0,
            9236.0,
            9180.0
        ],
        [
            4288.0,
            4379.0,
            4254.0,
            4355.0,
            4362.0
        ],
        [
            730.0,
            724.0,
            716.0,
            749.0,
            744.0
        ]
    ],
    "sim_time": 1.5430908203125
}