{
    "dni": 1000.0,
    "generated_rays": 103435326,
    "power_per_ray": 0.015056477785140635,
    "num_rays": 1836538.0,
    "avg_flux": 2708.1486487350535,
    "peak_flux": 5861.5127368569765,
    "min_flux": 0.0,
    "radius": 0.0,
    "bin_size_x": 0.06807059529144252,
    "bin_size_y": 6.0,
    "xvalues": [
        -0.13614119058288504,
        -0.0680705952914425,
        2.7755575615628914e-17,
        0.06807059529144252,
        0.13614119058288507
    ],
    "yvalues": [
        -12.0,
        -6.0,
        0.0,
        6.0,
        12.0
    ],
    "flux": [
        [
            0.0,
            89383.0,
            109572.0,
            109725.0,
            109309.0
        ],
        [
            0.0,
            159000.0,
            153411.0,
            153277.0,
            152396.0
        ],
        [
            0.0,
            154891.0,
            104389.0,
            104282.0,
            104077.0
        ],
        [
            0.0,
            96309.0,
            45309.0,
            45592.0,
            45141.0
        ],
        [
            0.0,
            40348.0,
            20114.0,
            19933.0,
            20080.0
        ]
    ],
    "sim_time": 44.83455729484558
}