{
    "dni": 1000.0,
    "generated_rays": 966495,
    "power_per_ray": 1.422677505417053,
    "num_rays": 240029.0,
    "avg_flux": 33444.089182776144,
    "peak_flux": 80036.66610624628,
    "min_flux": 6141.125575371553,
    "radius": 0.0,
    "bin_size_x": 0.06807059529144252,
    "bin_size_y": 6.0,
    "xvalues": [
        -0.13614119058288504,
        -0.0680705952914425,
        2.7755575615628914e-17,
        0.06807059529144252,
        0.13614119058288507
    ],
    "yvalues": [
        -12.0,
        -6.0,
        0.0,
        6.0,
        12.0
    ],
    "flux": [
        [
            1857.0,
            1860.0,
            1854.0,
            1858.0,
            1763.0
        ],
        [
            10702.0,
            10727.0,
            10888.0,
            10758.0,
            10802.0
        ],
        [
            22697.0,
            22663.0,
            22977.0,
            22671.0,
            22621.0
        ],
        [
            10752.0,
            10832.0,
            10877.0,
            10930.0,
            10756.0
        ],
        [
            1792.0,
            1819.0,
            1847.0,
            1893.0,
            1833.0
        ]
    ],
    "sim_time": 3.9223930835723877
}