{
    "dni": 1000.0,
    "generated_rays": 1936761,
    "power_per_ray": 0.7099537297570814,
    "num_rays": 479844.0,
    "avg_flux": 33364.09169950693,
    "peak_flux": 79886.04433077417,
    "min_flux": 6150.027739893357,
    "radius": 0.0,
    "bin_size_x": 0.06807059529144252,
    "bin_size_y": 6.0,
    "xvalues": [
        -0.13614119058288504,
        -0.0680705952914425,
        2.7755575615628914e-17,
        0.06807059529144252,
        0.13614119058288507
    ],
    "yvalues": [
        -12.0,
        -6.0,
        0.0,
        6.0,
        12.0
    ],
    "flux": [
        [
            3675.0,
            3655.0,
            3728.0,
            3703.0,
            3642.0
        ],
        [
            21666.0,
            21675.0,
            21804.0,
            21496.0,
            21435.0
        ],
        [
            45355.0,
            45298.0,
            45957.0,
            45642.0,
            45254.0
        ],
        [
            21582.0,
            21323.0,
            21761.0,
            21628.0,
            21375.0
        ],
        [
            3761.0,
            3665.0,
            3632.0,
            3594.0,
            3538.0
        ]
    ],
    "sim_time": 7.760058164596558
}