{
    "dni": 1000.0,
    "generated_rays": 17230475,
    "power_per_ray": 0.09038472172808813,
    "num_rays": 306167.0,
    "avg_flux": 2710.207834365983,
    "peak_flux": 5864.930579256361,
    "min_flux": 0.0,
    "radius": 0.0,
    "bin_size_x": 0.06807059529144252,
    "bin_size_y": 6.0,
    "xvalues": [
        -0.13614119058288504,
        -0.0680705952914425,
        2.7755575615628914e-17,
        0.06807059529144252,
        0.13614119058288507
    ],
    "yvalues": [
        -12.0,
        -6.0,
        0.0,
        6.0,
        12.0
    ],
    "flux": [
        [
            0.0,
            14645.0,
            18206.0,
            18472.0,
            18338.0
        ],
        [
            0.0,
            26502.0,
            25479.0,
            25373.0,
            25183.0
        ],
        [
            0.0,
            25988.0,
            17519.0,
            17477.0,
            17419.0
        ],
        [
            0.0,
            15901.0,
            7616.0,
            7580.0,
            7519.0
        ],
        [
            0.0,
            6959.0,
            3263.0,
            3373.0,
            3355.0
        ]
    ],
    "sim_time": 28.186084985733032
}