{
    "dni": 1000.0,
    "generated_rays": 103468862,
    "power_per_ray": 0.015051597727225216,
    "num_rays": 1836736.0,
    "avg_flux": 2707.5627672269648,
    "peak_flux": 5861.5292733003425,
    "min_flux": 0.0,
    "radius": 0.0,
    "bin_size_x": 0.06807059529144252,
    "bin_size_y": 6.0,
    "xvalues": [
        -0.13614119058288504,
        -0.0680705952914425,
        2.7755575615628914e-17,
        0.06807059529144252,
        0.13614119058288507
    ],
    "yvalues": [
        -12.0,
        -6.0,
        0.0,
        6.0,
        12.0
    ],
    "flux": [
        [
            0.0,
            89437.0,
            109665.0,
            109725.0,
            109460.0
        ],
        [
            0.0,
            159052.0,
            153412.0,
            153108.0,
            152241.0
        ],
        [
            0.0,
            154953.0,
            104561.0,
            104168.0,
            104219.0
        ],
        [
            0.0,
            96059.0,
            45271.0,
            45754.0,
            45256.0
        ],
        [
            0.0,
            40285.0,
            20155.0,
            19894.0,
            20061.0
        ]
    ],
    "sim_time": 43.719451904296875
}