{
    "dni": 1000.0,
    "generated_rays": 20089851,
    "power_per_ray": 0.057508832140486535,
    "num_rays": 855301.0,
    "avg_flux": 4817.289210610038,
    "peak_flux": 10479.83061162308,
    "min_flux": 478.88405968439,
    "radius": 0.0,
    "bin_size_x": 0.06807059529144252,
    "bin_size_y": 6.0,
    "xvalues": [
        -0.13614119058288504,
        -0.0680705952914425,
        2.7755575615628914e-17,
        0.06807059529144252,
        0.13614119058288507
    ],
    "yvalues": [
        -12.0,
        -6.0,
        0.0,
        6.0,
        12.0
    ],
    "flux": [
        [
            39101.0,
            41170.0,
            41234.0,
            40783.0,
            41247.0
        ],
        [
            71512.0,
            73832.0,
            74427.0,
            73558.0,
            73751.0
        ],
        [
            42479.0,
            42652.0,
            42731.0,
            43023.0,
            42133.0
        ],
        [
            11193.0,
            10721.0,
            10858.0,
            10713.0,
            10884.0
        ],
        [
            3401.0,
            3428.0,
            3524.0,
            3504.0,
            3442.0
        ]
    ],
    "sim_time": 13.973833322525024
}