{
    "dni": 1000.0,
    "generated_rays": 5747759,
    "power_per_ray": 0.24150149327666914,
    "num_rays": 872377.0,
    "avg_flux": 20633.515083196424,
    "peak_flux": 64632.21652361264,
    "min_flux": 1621.3488651731016,
    "radius": 0.0,
    "bin_size_x": 0.06807059529144252,
    "bin_size_y": 6.0,
    "xvalues": [
        -0.13614119058288504,
        -0.0680705952914425,
        2.7755575615628914e-17,
        0.06807059529144252,
        0.13614119058288507
    ],
    "yvalues": [
        -12.0,
        -6.0,
        0.0,
        6.0,
        12.0
    ],
    "flux": [
        [
            2742.0,
            5942.0,
            5963.0,
            5813.0,
            5978.0
        ],
        [
            18757.0,
            36437.0,
            36578.0,
            36316.0,
            36561.0
        ],
        [
            57174.0,
            109090.0,
            109305.0,
            108817.0,
            108823.0
        ],
        [
            16725.0,
            34602.0,
            34699.0,
            34961.0,
            34237.0
        ],
        [
            3197.0,
            7500.0,
            7382.0,
            7445.0,
            7333.0
        ]
    ],
    "sim_time": 8.92384123802185
}