{
    "dni": 1000.0,
    "generated_rays": 4378604,
    "power_per_ray": 0.33115321739377157,
    "num_rays": 901352.0,
    "avg_flux": 29232.946916002154,
    "peak_flux": 121786.6482398438,
    "min_flux": 5.675658022948168,
    "radius": 0.0,
    "bin_size_x": 0.06807059529144252,
    "bin_size_y": 6.0,
    "xvalues": [
        -0.13614119058288504,
        -0.0680705952914425,
        2.7755575615628914e-17,
        0.06807059529144252,
        0.13614119058288507
    ],
    "yvalues": [
        -12.0,
        -6.0,
        0.0,
        6.0,
        12.0
    ],
    "flux": [
        [
            124.0,
            230.0,
            245.0,
            225.0,
            228.0
        ],
        [
            13466.0,
            22992.0,
            22728.0,
            22848.0,
            22729.0
        ],
        [
            99138.0,
            150007.0,
            150052.0,
            150204.0,
            149907.0
        ],
        [
            12790.0,
            20758.0,
            20758.0,
            20953.0,
            20901.0
        ],
        [
            7.0,
            10.0,
            13.0,
            18.0,
            21.0
        ]
    ],
    "sim_time": 16.267091274261475
}