{
    "dni": 1000.0,
    "generated_rays": 5729514,
    "power_per_ray": 0.22006640952942064,
    "num_rays": 931978.0,
    "avg_flux": 20086.700808407564,
    "peak_flux": 57923.58895823242,
    "min_flux": 3018.4644360891343,
    "radius": 0.0,
    "bin_size_x": 0.06807059529144252,
    "bin_size_y": 6.0,
    "xvalues": [
        -0.13614119058288504,
        -0.0680705952914425,
        2.7755575615628914e-17,
        0.06807059529144252,
        0.13614119058288507
    ],
    "yvalues": [
        -12.0,
        -6.0,
        0.0,
        6.0,
        12.0
    ],
    "flux": [
        [
            6817.0,
            8245.0,
            8117.0,
            8077.0,
            8106.0
        ],
        [
            34090.0,
            40208.0,
            40024.0,
            40030.0,
            39514.0
        ],
        [
            90913.0,
            107486.0,
            107501.0,
            106946.0,
            107238.0
        ],
        [
            24779.0,
            30028.0,
            30182.0,
            29839.0,
            29818.0
        ],
        [
            5602.0,
            6903.0,
            7106.0,
            7187.0,
            7222.0
        ]
    ],
    "sim_time": 9.189183950424194
}