{
    "dni": 1000.0,
    "generated_rays": 5144267,
    "power_per_ray": 0.30292828330293253,
    "num_rays": 812615.0,
    "avg_flux": 24108.70321536706,
    "peak_flux": 107988.73861990558,
    "min_flux": 0.0,
    "radius": 0.0,
    "bin_size_x": 0.06807059529144252,
    "bin_size_y": 6.0,
    "xvalues": [
        -0.13614119058288504,
        -0.0680705952914425,
        2.7755575615628914e-17,
        0.06807059529144252,
        0.13614119058288507
    ],
    "yvalues": [
        -12.0,
        -6.0,
        0.0,
        6.0,
        12.0
    ],
    "flux": [
        [
            0.0,
            0.0,
            0.0,
            0.0,
            0.0
        ],
        [
            2872.0,
            23821.0,
            23907.0,
            23705.0,
            23823.0
        ],
        [
            31394.0,
            145596.0,
            144614.0,
            145300.0,
            144134.0
        ],
        [
            3014.0,
            25151.0,
            24950.0,
            24992.0,
            25147.0
        ],
        [
            0.0,
            40.0,
            55.0,
            48.0,
            52.0
        ]
    ],
    "sim_time": 8.776735544204712
}