{
    "dni": 1000.0,
    "generated_rays": 20464889,
    "power_per_ray": 0.0576565906124284,
    "num_rays": 846629.0,
    "avg_flux": 4780.6977882902165,
    "peak_flux": 10396.362769838765,
    "min_flux": 466.42110926128424,
    "radius": 0.0,
    "bin_size_x": 0.06807059529144252,
    "bin_size_y": 6.0,
    "xvalues": [
        -0.13614119058288504,
        -0.0680705952914425,
        2.7755575615628914e-17,
        0.06807059529144252,
        0.13614119058288507
    ],
    "yvalues": [
        -12.0,
        -6.0,
        0.0,
        6.0,
        12.0
    ],
    "flux": [
        [
            3472.0,
            3442.0,
            3304.0,
            3451.0,
            3412.0
        ],
        [
            11247.0,
            10619.0,
            10563.0,
            10725.0,
            10579.0
        ],
        [
            42154.0,
            42515.0,
            42392.0,
            42691.0,
            42269.0
        ],
        [
            68740.0,
            73554.0,
            73544.0,
            73645.0,
            73520.0
        ],
        [
            36729.0,
            40837.0,
            40636.0,
            41170.0,
            41419.0
        ]
    ],
    "sim_time": 21.12890338897705
}