{
    "dni": 1000.0,
    "generated_rays": 16367857,
    "power_per_ray": 0.10478274335975338,
    "num_rays": 135241.0,
    "avg_flux": 1387.8653412724402,
    "peak_flux": 10425.589110049497,
    "min_flux": 0.0,
    "radius": 0.0,
    "bin_size_x": 0.06807059529144252,
    "bin_size_y": 6.0,
    "xvalues": [
        -0.13614119058288504,
        -0.0680705952914425,
        2.7755575615628914e-17,
        0.06807059529144252,
        0.13614119058288507
    ],
    "yvalues": [
        -12.0,
        -6.0,
        0.0,
        6.0,
        12.0
    ],
    "flux": [
        [
            0.0,
            0.0,
            0.0,
            353.0,
            6862.0
        ],
        [
            0.0,
            0.0,
            0.0,
            4744.0,
            32467.0
        ],
        [
            0.0,
            0.0,
            0.0,
            6387.0,
            40637.0
        ],
        [
            0.0,
            0.0,
            0.0,
            4868.0,
            32119.0
        ],
        [
            0.0,
            0.0,
            0.0,
            391.0,
            6413.0
        ]
    ],
    "sim_time": 18.403693437576294
}