{
    "dni": 1000.0,
    "generated_rays": 58493203,
    "power_per_ray": 0.01873167139198213,
    "num_rays": 416952.0,
    "avg_flux": 437.10365154701134,
    "peak_flux": 2215.0182883249877,
    "min_flux": 0.0,
    "radius": 0.0,
    "bin_size_x": 0.11912060709304066,
    "bin_size_y": 6.0,
    "xvalues": [
        -0.23824121418608132,
        -0.11912060709304068,
        0.0,
        0.11912060709304068,
        0.23824121418608135
    ],
    "yvalues": [
        -12.0,
        -6.0,
        0.0,
        6.0,
        12.0
    ],
    "flux": [
        [
            0.0,
            0.0,
            77.0,
            127.0,
            101.0
        ],
        [
            0.0,
            0.0,
            18270.0,
            37278.0,
            37484.0
        ],
        [
            0.0,
            0.0,
            41673.0,
            84190.0,
            84516.0
        ],
        [
            0.0,
            0.0,
            22457.0,
            44918.0,
            44772.0
        ],
        [
            0.0,
            0.0,
            182.0,
            440.0,
            467.0
        ]
    ],
    "sim_time": 47.78290557861328
}